lektor_mistune_smartypants.py
lektor_mistune_smartypants-1.0.dist-info/METADATA
lektor_mistune_smartypants-1.0.dist-info/WHEEL
lektor_mistune_smartypants-1.0.dist-info/entry_points.txt
lektor_mistune_smartypants-1.0.dist-info/top_level.txt
lektor_mistune_smartypants-1.0.dist-info/RECORD
