Metadata-Version: 2.1
Name: lektor-mistune-smartypants
Version: 1.0
Summary: Adds curly quotes to your markdown paragraphs and headings.
Home-page: https://github.com/jeanpaul/lektor-mistune-smartypants
Author: Jean-Paul van Oosten
Author-email: pypi@jpvanoosten.nl
License: MIT
Keywords: smartypants lektor
Platform: UNKNOWN
Classifier: Framework :: Lektor
Classifier: Environment :: Plugins
Classifier: License :: OSI Approved :: MIT License
Requires-Dist: smartypants
